plogchain/__init__.py
plogchain/formatters/Basic.py
plogchain/formatters/Csv.py
plogchain/formatters/Json.py
plogchain/formatters/__init__.py
plogchain-0.1.1.dist-info/LICENSE
plogchain-0.1.1.dist-info/WHEEL
plogchain-0.1.1.dist-info/METADATA
plogchain-0.1.1.dist-info/RECORD
