Metadata-Version: 2.1
Name: plogchain
Version: 0.1.1
Summary: Python Logging based on blockchain
Home-page: https://gg-math.github.io/plogchain
License: ISC
Keywords: logging,security,secure,blockchain,signature
Author: Gg Math
Author-email: code@gmath.io
Requires-Python: >=3.2,<4.0
Classifier: License :: OSI Approved
Classifier: Programming Language :: Python :: 3
Classifier: Programming Language :: Python :: 3.4
Classifier: Programming Language :: Python :: 3.5
Classifier: Programming Language :: Python :: 3.6
Classifier: Programming Language :: Python :: 3.7
Classifier: Programming Language :: Python :: 3.8
Requires-Dist: toml (>=0.9,<0.10)
Project-URL: Repository, https://github.com/gg-math/plogchain
